nbtest_lab_extension/__init__.py
nbtest_lab_extension-0.2.5.data/data/share/jupyter/labextensions/nbtest_lab_extension/build_log.json
nbtest_lab_extension-0.2.5.data/data/share/jupyter/labextensions/nbtest_lab_extension/package.json
nbtest_lab_extension-0.2.5.data/data/share/jupyter/labextensions/nbtest_lab_extension/static/lib_index_js-webpack_sharing_consume_default_codemirror_language-webpack_sharing_consume_defa-b29f5c.6cf01cad86edf365d9ac.js
nbtest_lab_extension-0.2.5.data/data/share/jupyter/labextensions/nbtest_lab_extension/static/lib_index_js-webpack_sharing_consume_default_codemirror_language-webpack_sharing_consume_defa-b29f5c.6cf01cad86edf365d9ac.js.map
nbtest_lab_extension-0.2.5.data/data/share/jupyter/labextensions/nbtest_lab_extension/static/remoteEntry.187048224567a4a1c8b8.js
nbtest_lab_extension-0.2.5.data/data/share/jupyter/labextensions/nbtest_lab_extension/static/remoteEntry.187048224567a4a1c8b8.js.map
nbtest_lab_extension-0.2.5.data/data/share/jupyter/labextensions/nbtest_lab_extension/static/style.js
nbtest_lab_extension-0.2.5.data/data/share/jupyter/labextensions/nbtest_lab_extension/static/style_index_js.505f50ae8740e8225a75.js
nbtest_lab_extension-0.2.5.data/data/share/jupyter/labextensions/nbtest_lab_extension/static/style_index_js.505f50ae8740e8225a75.js.map
nbtest_lab_extension-0.2.5.data/data/share/jupyter/labextensions/nbtest_lab_extension/static/vendors-node_modules_codemirror_commands_dist_index_js-node_modules_codemirror_lang-python_di-16a749.85f2668a31fe4b1aaff0.js
nbtest_lab_extension-0.2.5.data/data/share/jupyter/labextensions/nbtest_lab_extension/static/vendors-node_modules_codemirror_commands_dist_index_js-node_modules_codemirror_lang-python_di-16a749.85f2668a31fe4b1aaff0.js.map
nbtest_lab_extension-0.2.5.data/data/share/jupyter/labextensions/nbtest_lab_extension/install.json
nbtest_lab_extension-0.2.5.dist-info/METADATA
nbtest_lab_extension-0.2.5.dist-info/WHEEL
nbtest_lab_extension-0.2.5.dist-info/licenses/LICENSE
nbtest_lab_extension-0.2.5.dist-info/RECORD
